vistring/__init__.py
vistring/vistring.py
vistring-0.2.0.dist-info/DESCRIPTION.rst
vistring-0.2.0.dist-info/METADATA
vistring-0.2.0.dist-info/RECORD
vistring-0.2.0.dist-info/WHEEL
vistring-0.2.0.dist-info/metadata.json
vistring-0.2.0.dist-info/top_level.txt
