Metadata-Version: 2.0
Name: vistring
Version: 0.2.0
Summary: Python library for handling Vietnamese string, especially with tones
Home-page: https://github.com/pymivn/vistring
Author: Viet Hung Nguyen
Author-email: hvn@familug.org
License: BSD license
Keywords: vistring
Platform: UNKNOWN
Classifier: Development Status :: 2 - Pre-Alpha
Classifier: Intended Audience :: Developers
Classifier: License :: OSI Approved :: BSD License
Classifier: Natural Language :: English
Classifier: Programming Language :: Python :: 2
Classifier: Programming Language :: Python :: 2.6
Classifier: Programming Language :: Python :: 2.7
Classifier: Programming Language :: Python :: 3
Classifier: Programming Language :: Python :: 3.3
Classifier: Programming Language :: Python :: 3.4
Classifier: Programming Language :: Python :: 3.5
